{
    "type": "object",
    "properties": {
        "access_token": {
            "type": "string"
        },
        "alt": {
            "type": "string",
            "enum": [
                "json",
                "media",
                "proto"
            ],
            "default": "json"
        },
        "callback": {
            "type": "string"
        },
        "fields": {
            "type": "string"
        },
        "key": {
            "type": "string"
        },
        "oauth_token": {
            "type": "string"
        },
        "prettyPrint": {
            "type": "boolean",
            "default": true
        },
        "quotaUser": {
            "type": "string"
        },
        "uploadType": {
            "type": "string"
        },
        "upload_protocol": {
            "type": "string"
        },
        "__xgafv": {
            "type": "string",
            "enum": [
                "1",
                "2"
            ]
        }
    }
}